eopkg3p/__init__.py
eopkg3p/__version__.py
eopkg3p/cli.py
eopkg3p/consts.py
eopkg3p/core.py
eopkg3p-0.0.6.dist-info/METADATA
eopkg3p-0.0.6.dist-info/WHEEL
eopkg3p-0.0.6.dist-info/entry_points.txt
eopkg3p-0.0.6.dist-info/top_level.txt
eopkg3p-0.0.6.dist-info/RECORD
