Metadata-Version: 2.1
Name: eopkg3p
Version: 0.0.6
Summary: CLI and python API for the Solus 3rd party packages.
Home-page: https://github.com/pycampers/eopkg3p
Author: Dev Aggarwal
Author-email: devxpy@gmail.com
License: MIT
Platform: UNKNOWN
Classifier: License :: OSI Approved :: MIT License
Classifier: Programming Language :: Python
Classifier: Programming Language :: Python :: 3
Classifier: Programming Language :: Python :: 3.6
Classifier: Programming Language :: Python :: Implementation :: CPython
Classifier: Programming Language :: Python :: Implementation :: PyPy
Requires-Python: >=3.6.0
Requires-Dist: crayons
Requires-Dist: click
